brewmytea/__init__.py
brewmytea/brewmytea.py
brewmytea/cli.py
brewmytea-0.1.0.dist-info/AUTHORS.rst
brewmytea-0.1.0.dist-info/LICENSE
brewmytea-0.1.0.dist-info/METADATA
brewmytea-0.1.0.dist-info/WHEEL
brewmytea-0.1.0.dist-info/entry_points.txt
brewmytea-0.1.0.dist-info/top_level.txt
brewmytea-0.1.0.dist-info/RECORD
