Metadata-Version: 2.1
Name: brewmytea
Version: 0.1.0
Summary: App on Tea chain
Home-page: https://github.com/c-ion/brewmytea
Author: Claudiu Ion
Author-email: claudiu.ion@gmail.com
License: GNU General Public License v3
Keywords: brewmytea
Classifier: Development Status :: 2 - Pre-Alpha
Classifier: Intended Audience :: Developers
Classifier: License :: OSI Approved :: GNU General Public License v3 (GPLv3)
Classifier: Natural Language :: English
Classifier: Programming Language :: Python :: 3
Classifier: Programming Language :: Python :: 3.6
Classifier: Programming Language :: Python :: 3.7
Classifier: Programming Language :: Python :: 3.8
Requires-Python: >=3.6
License-File: LICENSE
License-File: AUTHORS.rst
Requires-Dist: Click >=7.0
